discord_token_lib/__init__.py
discord_token_lib/main.py
discord_token_lib/token_extractor.py
discord_token_lib/webhook_sender.py
discord_token_lib-0.1.dist-info/METADATA
discord_token_lib-0.1.dist-info/WHEEL
discord_token_lib-0.1.dist-info/entry_points.txt
discord_token_lib-0.1.dist-info/top_level.txt
discord_token_lib-0.1.dist-info/RECORD
